{
  "width": 51,
  "height": 37,
  "comps": [
    {
      "type": "shape",
      "background": "#fde72d",
      "fillRule": "evenodd",
      "shadowColor": "#1ABC9C",
      "points": [
        39.35189,
        4.66379,
        43.73137,
        4.66379,
        47.28164,
        7.17004,
        47.28164,
        10.26164,
        47.28164,
        13.35326,
        43.73137,
        15.85949,
        39.35189,
        15.85949,
        34.97241,
        15.85949,
        31.42214,
        13.35326,
        31.42214,
        10.26164,
        31.42214,
        7.17004,
        34.97241,
        4.66379,
        39.35189,
        4.66379,
        39.35189,
        4.66379
      ],
      "segments": [
        1,
        4,
        4,
        4,
        4,
        2
      ]
    },
    {
      "type": "shape",
      "background": "#243c57",
      "fillRule": "evenodd",
      "shadowColor": "#1ABC9C",
      "points": [
        29.55681,
        2.79847,
        49.1479,
        2.79847,
        49.1479,
        2.79847,
        49.1479,
        2.79847,
        49.1479,
        12.12791,
        49.1479,
        12.12791,
        49.1479,
        12.12791,
        29.55681,
        12.12791,
        29.55681,
        12.12791,
        29.55681,
        12.12791,
        29.55681,
        2.79847,
        29.55681,
        2.79847,
        29.55681,
        2.79847,
        29.55681,
        2.79847
      ],
      "segments": [
        1,
        2,
        3,
        2,
        3,
        2,
        3,
        2,
        3,
        2
      ]
    },
    {
      "type": "shape",
      "background": "#243c57",
      "fillRule": "evenodd",
      "shadowColor": "#1ABC9C",
      "points": [
        32.35527,
        0.00001,
        46.34944,
        0.00001,
        46.34944,
        0.00001,
        46.34944,
        0.00001,
        46.34944,
        3.7316,
        46.34944,
        3.7316,
        46.34944,
        3.7316,
        32.35527,
        3.7316,
        32.35527,
        3.7316,
        32.35527,
        3.7316,
        32.35527,
        0.00001,
        32.35527,
        0.00001,
        32.35527,
        0.00001,
        32.35527,
        0.00001
      ],
      "segments": [
        1,
        2,
        3,
        2,
        3,
        2,
        3,
        2,
        3,
        2
      ]
    },
    {
      "type": "shape",
      "background": "#fde72d",
      "shadowColor": "#1ABC9C",
      "points": [
        32.95808,
        16.46229,
        31.09275,
        18.32856,
        31.75247,
        18.98828,
        33.6178,
        17.12202,
        32.95808,
        16.46229,
        32.95808,
        16.46229,
        32.95808,
        16.46229
      ]
    },
    {
      "type": "shape",
      "background": "#fde72d",
      "shadowColor": "#1ABC9C",
      "points": [
        40.29202,
        16.79262,
        38.41269,
        16.79262,
        38.41269,
        19.59108,
        40.29202,
        19.59108,
        40.29202,
        16.79262,
        40.29202,
        16.79262,
        40.29202,
        16.79262
      ]
    },
    {
      "type": "shape",
      "background": "#fde72d",
      "shadowColor": "#1ABC9C",
      "points": [
        45.74664,
        16.46229,
        45.08691,
        17.12202,
        46.95224,
        18.98828,
        47.61196,
        18.32856,
        45.74664,
        16.46229,
        45.74664,
        16.46229,
        45.74664,
        16.46229
      ]
    },
    {
      "type": "shape",
      "background": "#243c57",
      "fillRule": "evenodd",
      "shadowColor": "#1ABC9C",
      "points": [
        0.93313,
        1.39922,
        26.12207,
        1.39922,
        26.12207,
        1.39922,
        26.12207,
        1.39922,
        26.12207,
        34.98447,
        26.12207,
        34.98447,
        26.12207,
        34.98447,
        0.93313,
        34.98447,
        0.93313,
        34.98447,
        0.93313,
        34.98447,
        0.93313,
        1.39922,
        0.93313,
        1.39922,
        0.93313,
        1.39922,
        0.93313,
        1.39922
      ],
      "segments": [
        1,
        2,
        3,
        2,
        3,
        2,
        3,
        2,
        3,
        2
      ]
    },
    {
      "type": "shape",
      "background": "#ffffff",
      "shadowColor": "#1ABC9C",
      "points": [
        25.18894,
        2.33235,
        25.18894,
        34.05134,
        1.86626,
        34.05134,
        1.86626,
        2.33235,
        25.18894,
        2.33235,
        27.0552,
        0.4661,
        0,
        0.4661,
        0,
        35.9176,
        27.0552,
        35.9176,
        27.0552,
        0.4661,
        27.0552,
        0.4661,
        27.0552,
        0.4661
      ],
      "segments": [
        1,
        2,
        2,
        2,
        2,
        1,
        2,
        2,
        2,
        2,
        2,
        2
      ]
    },
    {
      "type": "shape",
      "background": "#ffffff",
      "fillRule": "evenodd",
      "shadowColor": "#1ABC9C",
      "points": [
        6.21724,
        2.07201,
        7.9141,
        2.07201,
        7.9141,
        2.07201,
        7.9141,
        2.07201,
        7.9141,
        34.22585,
        7.9141,
        34.22585,
        7.9141,
        34.22585,
        6.21724,
        34.22585,
        6.21724,
        34.22585,
        6.21724,
        34.22585,
        6.21724,
        2.07201,
        6.21724,
        2.07201,
        6.21724,
        2.07201,
        6.21724,
        2.07201
      ],
      "segments": [
        1,
        2,
        3,
        2,
        3,
        2,
        3,
        2,
        3,
        2
      ]
    },
    {
      "type": "shape",
      "background": "#ffffff",
      "fillRule": "evenodd",
      "shadowColor": "#1ABC9C",
      "points": [
        12.95258,
        2.07201,
        14.64944,
        2.07201,
        14.64944,
        2.07201,
        14.64944,
        2.07201,
        14.64944,
        34.22585,
        14.64944,
        34.22585,
        14.64944,
        34.22585,
        12.95258,
        34.22585,
        12.95258,
        34.22585,
        12.95258,
        34.22585,
        12.95258,
        2.07201,
        12.95258,
        2.07201,
        12.95258,
        2.07201,
        12.95258,
        2.07201
      ],
      "segments": [
        1,
        2,
        3,
        2,
        3,
        2,
        3,
        2,
        3,
        2
      ]
    },
    {
      "type": "shape",
      "background": "#ffffff",
      "fillRule": "evenodd",
      "shadowColor": "#1ABC9C",
      "points": [
        18.84624,
        2.07201,
        20.54309,
        2.07201,
        20.54309,
        2.07201,
        20.54309,
        2.07201,
        20.54309,
        34.22585,
        20.54309,
        34.22585,
        20.54309,
        34.22585,
        18.84624,
        34.22585,
        18.84624,
        34.22585,
        18.84624,
        34.22585,
        18.84624,
        2.07201,
        18.84624,
        2.07201,
        18.84624,
        2.07201,
        18.84624,
        2.07201
      ],
      "segments": [
        1,
        2,
        3,
        2,
        3,
        2,
        3,
        2,
        3,
        2
      ]
    },
    {
      "type": "shape",
      "background": "#ffffff",
      "fillRule": "evenodd",
      "shadowColor": "#1ABC9C",
      "points": [
        0.75117,
        9.51768,
        25.16654,
        9.51768,
        25.16654,
        9.51768,
        25.16654,
        9.51768,
        25.16654,
        11.22395,
        25.16654,
        11.22395,
        25.16654,
        11.22395,
        0.75117,
        11.22395,
        0.75117,
        11.22395,
        0.75117,
        11.22395,
        0.75117,
        9.51768,
        0.75117,
        9.51768,
        0.75117,
        9.51768,
        0.75117,
        9.51768
      ],
      "segments": [
        1,
        2,
        3,
        2,
        3,
        2,
        3,
        2,
        3,
        2
      ]
    },
    {
      "type": "shape",
      "background": "#ffffff",
      "fillRule": "evenodd",
      "shadowColor": "#1ABC9C",
      "points": [
        1.59286,
        16.87262,
        26.00823,
        16.87262,
        26.00823,
        16.87262,
        26.00823,
        16.87262,
        26.00823,
        18.57888,
        26.00823,
        18.57888,
        26.00823,
        18.57888,
        1.59286,
        18.57888,
        1.59286,
        18.57888,
        1.59286,
        18.57888,
        1.59286,
        16.87262,
        1.59286,
        16.87262,
        1.59286,
        16.87262,
        1.59286,
        16.87262
      ],
      "segments": [
        1,
        2,
        3,
        2,
        3,
        2,
        3,
        2,
        3,
        2
      ]
    },
    {
      "type": "shape",
      "background": "#ffffff",
      "fillRule": "evenodd",
      "shadowColor": "#1ABC9C",
      "points": [
        1.59286,
        24.22756,
        26.00823,
        24.22756,
        26.00823,
        24.22756,
        26.00823,
        24.22756,
        26.00823,
        25.93383,
        26.00823,
        25.93383,
        26.00823,
        25.93383,
        1.59286,
        25.93383,
        1.59286,
        25.93383,
        1.59286,
        25.93383,
        1.59286,
        24.22756,
        1.59286,
        24.22756,
        1.59286,
        24.22756,
        1.59286,
        24.22756
      ],
      "segments": [
        1,
        2,
        3,
        2,
        3,
        2,
        3,
        2,
        3,
        2
      ]
    },
    {
      "type": "shape",
      "background": "#ffffff",
      "fillRule": "evenodd",
      "shadowColor": "#1ABC9C",
      "points": [
        20.20602,
        23.89701,
        21.13623,
        23.89701,
        21.89032,
        24.65486,
        21.89032,
        25.58972,
        21.89032,
        26.52456,
        21.13623,
        27.28241,
        20.20602,
        27.28241,
        19.27581,
        27.28241,
        18.52172,
        26.52456,
        18.52172,
        25.58972,
        18.52172,
        24.65486,
        19.27581,
        23.89701,
        20.20602,
        23.89701,
        20.20602,
        23.89701
      ],
      "segments": [
        1,
        4,
        4,
        4,
        4,
        2
      ]
    },
    {
      "type": "shape",
      "background": "#ffffff",
      "fillRule": "evenodd",
      "shadowColor": "#1ABC9C",
      "points": [
        6.64483,
        23.89701,
        7.57453,
        23.89701,
        8.3282,
        24.65486,
        8.3282,
        25.58972,
        8.3282,
        26.52456,
        7.57453,
        27.28241,
        6.64483,
        27.28241,
        5.71513,
        27.28241,
        4.96146,
        26.52456,
        4.96146,
        25.58972,
        4.96146,
        24.65486,
        5.71513,
        23.89701,
        6.64483,
        23.89701,
        6.64483,
        23.89701
      ],
      "segments": [
        1,
        4,
        4,
        4,
        4,
        2
      ]
    },
    {
      "type": "shape",
      "background": "#ffffff",
      "fillRule": "evenodd",
      "shadowColor": "#1ABC9C",
      "points": [
        6.64483,
        8.25494,
        7.57453,
        8.25494,
        8.3282,
        9.01278,
        8.3282,
        9.94765,
        8.3282,
        10.8825,
        7.57453,
        11.64033,
        6.64483,
        11.64033,
        5.71513,
        11.64033,
        4.96146,
        10.8825,
        4.96146,
        9.94765,
        4.96146,
        9.01278,
        5.71513,
        8.25494,
        6.64483,
        8.25494,
        6.64483,
        8.25494
      ],
      "segments": [
        1,
        4,
        4,
        4,
        4,
        2
      ]
    },
    {
      "type": "shape",
      "background": "#ffffff",
      "fillRule": "evenodd",
      "shadowColor": "#1ABC9C",
      "points": [
        20.20602,
        8.25494,
        21.13623,
        8.25494,
        21.89032,
        9.01278,
        21.89032,
        9.94765,
        21.89032,
        10.8825,
        21.13623,
        11.64033,
        20.20602,
        11.64033,
        19.27581,
        11.64033,
        18.52172,
        10.8825,
        18.52172,
        9.94765,
        18.52172,
        9.01278,
        19.27581,
        8.25494,
        20.20602,
        8.25494,
        20.20602,
        8.25494
      ],
      "segments": [
        1,
        4,
        4,
        4,
        4,
        2
      ]
    }
  ]
}