{
  "width": 549,
  "height": 639,
  "comps": [
    {
      "type": "shape",
      "background": "#e5e5e5",
      "shadowColor": "#1ABC9C",
      "rotation": -3.14159,
      "points": [
        376.43888,
        504.52386,
        479.33644,
        466.17695,
        517.68335,
        466.17695,
        531.10477,
        478.95925,
        531.10477,
        517.94529,
        492.11874,
        556.2922,
        505.54016,
        568.43539,
        505.54016,
        606.78231,
        492.11874,
        620.20373,
        108.01048,
        620.20373,
        94.58906,
        606.78231,
        94.58906,
        568.43539,
        108.01048,
        556.2922,
        69.66356,
        517.94529,
        69.66356,
        478.95925,
        82.44587,
        466.17695,
        120.15367,
        466.17695,
        223.69034,
        504.52386,
        376.43888,
        504.52386,
        376.43888,
        504.52386
      ]
    },
    {
      "type": "shape",
      "background": "#cccccc",
      "shadowColor": "#1ABC9C",
      "rotation": -3.14159,
      "points": [
        224.32945,
        581.85681,
        377.078,
        581.85681,
        377.078,
        543.5099,
        224.32945,
        543.5099,
        224.32945,
        581.85681,
        224.32945,
        581.85681
      ]
    },
    {
      "type": "shape",
      "background": "#999999",
      "shadowColor": "#1ABC9C",
      "rotation": -3.14159,
      "points": [
        480.61467,
        620.20373,
        377.078,
        581.85681,
        377.078,
        543.5099,
        480.61467,
        581.85681,
        480.61467,
        620.20373,
        480.61467,
        620.20373
      ]
    },
    {
      "type": "shape",
      "background": "#cccccc",
      "shadowColor": "#1ABC9C",
      "rotation": -3.14159,
      "points": [
        480.61467,
        620.20373,
        518.32247,
        620.20373,
        518.32247,
        581.85681,
        480.61467,
        581.85681,
        480.61467,
        620.20373,
        480.61467,
        620.20373
      ]
    },
    {
      "type": "shape",
      "background": "#b2b2b2",
      "shadowColor": "#1ABC9C",
      "rotation": -3.14159,
      "points": [
        121.4319,
        620.20373,
        224.32945,
        581.85681,
        224.32945,
        543.5099,
        121.4319,
        581.85681,
        121.4319,
        620.20373,
        121.4319,
        620.20373
      ]
    },
    {
      "type": "shape",
      "background": "#cccccc",
      "shadowColor": "#1ABC9C",
      "rotation": -3.14159,
      "points": [
        83.08498,
        620.20373,
        121.4319,
        620.20373,
        121.4319,
        581.85681,
        83.08498,
        581.85681,
        83.08498,
        620.20373,
        83.08498,
        620.20373
      ]
    },
    {
      "type": "shape",
      "background": "#b2b2b2",
      "shadowColor": "#1ABC9C",
      "rotation": -3.14159,
      "points": [
        531.10477,
        606.78231,
        518.32247,
        620.20373,
        518.32247,
        581.21769,
        531.10477,
        568.43539,
        531.10477,
        606.78231,
        531.10477,
        606.78231
      ]
    },
    {
      "type": "shape",
      "background": "#999999",
      "shadowColor": "#1ABC9C",
      "rotation": -3.14159,
      "points": [
        83.08498,
        620.20373,
        69.66356,
        606.78231,
        69.66356,
        568.43539,
        83.08498,
        581.21769,
        83.08498,
        620.20373,
        83.08498,
        620.20373
      ]
    },
    {
      "type": "shape",
      "background": "#b2b2b2",
      "shadowColor": "#1ABC9C",
      "rotation": -3.14159,
      "points": [
        506.17928,
        517.30617,
        492.75786,
        530.08847,
        492.75786,
        491.74156,
        506.17928,
        479.59837,
        506.17928,
        517.30617,
        506.17928,
        517.30617
      ]
    },
    {
      "type": "shape",
      "background": "#999999",
      "shadowColor": "#1ABC9C",
      "rotation": -3.14159,
      "points": [
        108.64959,
        530.08847,
        95.22817,
        517.30617,
        95.22817,
        479.59837,
        108.64959,
        491.74156,
        108.64959,
        530.08847,
        108.64959,
        530.08847
      ]
    },
    {
      "type": "shape",
      "borderWidth": 1.27823,
      "borderColor": "#000000",
      "shadowColor": "#1ABC9C",
      "rotation": -3.14159,
      "points": [
        531.10477,
        556.93132,
        517.68335,
        543.5099,
        479.33644,
        543.5099,
        376.43888,
        581.85681,
        223.69034,
        581.85681,
        120.15367,
        543.5099,
        82.44587,
        543.5099,
        69.66356,
        556.93132
      ]
    },
    {
      "type": "shape",
      "borderWidth": 1.27823,
      "borderColor": "#000000",
      "shadowColor": "#1ABC9C",
      "rotation": -3.14159,
      "points": [
        376.43888,
        504.52386,
        479.33644,
        466.17695,
        517.68335,
        466.17695,
        531.10477,
        478.95925,
        531.10477,
        517.94529,
        492.11874,
        556.2922,
        505.54016,
        568.43539,
        505.54016,
        606.78231,
        492.11874,
        620.20373,
        108.01048,
        620.20373,
        94.58906,
        606.78231,
        94.58906,
        568.43539,
        108.01048,
        556.2922,
        69.66356,
        517.94529,
        69.66356,
        478.95925,
        82.44587,
        466.17695,
        120.15367,
        466.17695,
        223.69034,
        504.52386,
        376.43888,
        504.52386
      ]
    },
    {
      "type": "shape",
      "background": "#4c4c4c",
      "shadowColor": "#1ABC9C",
      "rotation": -3.14159,
      "points": [
        480.61467,
        568.43539,
        506.17928,
        568.43539,
        506.17928,
        562.68335,
        480.61467,
        562.68335,
        480.61467,
        568.43539,
        480.61467,
        568.43539
      ]
    },
    {
      "type": "shape",
      "background": "#4c4c4c",
      "shadowColor": "#1ABC9C",
      "rotation": -3.14159,
      "points": [
        467.19325,
        556.2922,
        492.75786,
        556.2922,
        492.75786,
        549.26193,
        467.19325,
        549.26193,
        467.19325,
        556.2922,
        467.19325,
        556.2922
      ]
    },
    {
      "type": "shape",
      "background": "#4c4c4c",
      "shadowColor": "#1ABC9C",
      "rotation": -3.14159,
      "points": [
        95.22817,
        568.43539,
        121.4319,
        568.43539,
        121.4319,
        562.68335,
        95.22817,
        562.68335,
        95.22817,
        568.43539,
        95.22817,
        568.43539
      ]
    },
    {
      "type": "shape",
      "background": "#4c4c4c",
      "shadowColor": "#1ABC9C",
      "rotation": -3.14159,
      "points": [
        114.40163,
        556.2922,
        140.60536,
        556.2922,
        140.60536,
        549.26193,
        114.40163,
        549.26193,
        114.40163,
        556.2922,
        114.40163,
        556.2922
      ]
    },
    {
      "type": "shape",
      "background": "#4c4c4c",
      "shadowColor": "#1ABC9C",
      "rotation": -3.14159,
      "points": [
        121.4319,
        485.35041,
        487.00582,
        485.35041,
        487.00582,
        479.59837,
        121.4319,
        479.59837,
        121.4319,
        485.35041,
        121.4319,
        485.35041
      ]
    },
    {
      "type": "shape",
      "background": "#4c4c4c",
      "shadowColor": "#1ABC9C",
      "rotation": -3.14159,
      "points": [
        56.24214,
        414.40861,
        108.64959,
        414.40861,
        108.64959,
        350.49709,
        56.24214,
        350.49709,
        56.24214,
        414.40861,
        56.24214,
        414.40861
      ]
    },
    {
      "type": "shape",
      "background": "#666666",
      "shadowColor": "#1ABC9C",
      "rotation": -3.14159,
      "points": [
        56.24214,
        185.60536,
        108.64959,
        185.60536,
        108.64959,
        350.49709,
        56.24214,
        350.49709,
        56.24214,
        185.60536,
        56.24214,
        185.60536
      ]
    },
    {
      "type": "shape",
      "background": "#7f7f7f",
      "shadowColor": "#1ABC9C",
      "rotation": -3.14159,
      "points": [
        56.24214,
        185.60536,
        108.64959,
        185.60536,
        108.64959,
        106.99418,
        56.24214,
        106.99418,
        56.24214,
        185.60536,
        56.24214,
        185.60536
      ]
    },
    {
      "type": "shape",
      "background": "#333333",
      "shadowColor": "#1ABC9C",
      "rotation": -3.14159,
      "points": [
        467.19325,
        390.12224,
        480.61467,
        390.12224,
        480.61467,
        146.61932,
        467.19325,
        146.61932,
        467.19325,
        390.12224,
        467.19325,
        390.12224
      ]
    },
    {
      "type": "shape",
      "background": "#4c4c4c",
      "shadowColor": "#1ABC9C",
      "rotation": -3.14159,
      "points": [
        480.61467,
        402.26542,
        531.10477,
        402.26542,
        531.10477,
        345.38417,
        480.61467,
        345.38417,
        480.61467,
        402.26542,
        480.61467,
        402.26542
      ]
    },
    {
      "type": "shape",
      "background": "#666666",
      "shadowColor": "#1ABC9C",
      "rotation": -3.14159,
      "points": [
        480.61467,
        204.77881,
        531.10477,
        204.77881,
        531.10477,
        345.38417,
        480.61467,
        345.38417,
        480.61467,
        204.77881,
        480.61467,
        204.77881
      ]
    },
    {
      "type": "shape",
      "background": "#7f7f7f",
      "shadowColor": "#1ABC9C",
      "rotation": -3.14159,
      "points": [
        480.61467,
        204.77881,
        531.10477,
        204.77881,
        531.10477,
        133.83702,
        480.61467,
        133.83702,
        480.61467,
        204.77881,
        480.61467,
        204.77881
      ]
    },
    {
      "type": "shape",
      "borderWidth": 1.27823,
      "borderColor": "#000000",
      "shadowColor": "#1ABC9C",
      "rotation": -3.14159,
      "points": [
        480.61467,
        402.26542,
        531.10477,
        402.26542,
        531.10477,
        133.83702,
        480.61467,
        133.83702,
        480.61467,
        402.26542
      ]
    },
    {
      "type": "shape",
      "background": "#4c4c4c",
      "shadowColor": "#1ABC9C",
      "rotation": -3.14159,
      "points": [
        160.41793,
        530.08847,
        454.41094,
        530.08847,
        454.41094,
        517.94529,
        160.41793,
        517.94529,
        160.41793,
        530.08847,
        160.41793,
        530.08847
      ]
    },
    {
      "type": "shape",
      "background": "#666666",
      "shadowColor": "#1ABC9C",
      "rotation": -3.14159,
      "points": [
        146.99651,
        517.94529,
        466.55413,
        517.94529,
        466.55413,
        106.99418,
        146.99651,
        106.99418,
        146.99651,
        517.94529,
        146.99651,
        517.94529
      ]
    },
    {
      "type": "shape",
      "background": "#616161",
      "shadowColor": "#1ABC9C",
      "rotation": -3.14159,
      "points": [
        146.99651,
        347.30151,
        466.55413,
        517.94529,
        466.55413,
        227.78696,
        146.99651,
        227.78696,
        146.99651,
        347.30151,
        146.99651,
        347.30151
      ]
    },
    {
      "type": "shape",
      "background": "#5c5c5c",
      "shadowColor": "#1ABC9C",
      "rotation": -3.14159,
      "points": [
        146.99651,
        346.6624,
        466.55413,
        517.94529,
        466.55413,
        244.40396,
        146.99651,
        244.40396,
        146.99651,
        346.6624,
        146.99651,
        346.6624
      ]
    },
    {
      "type": "shape",
      "background": "#575757",
      "shadowColor": "#1ABC9C",
      "rotation": -3.14159,
      "points": [
        146.99651,
        346.02328,
        466.55413,
        517.94529,
        466.55413,
        269.96857,
        146.99651,
        269.96857,
        146.99651,
        346.02328,
        146.99651,
        346.02328
      ]
    },
    {
      "type": "shape",
      "borderWidth": 1.27823,
      "borderColor": "#000000",
      "shadowColor": "#1ABC9C",
      "rotation": -3.14159,
      "points": [
        146.99651,
        517.94529,
        466.55413,
        517.94529,
        466.55413,
        106.99418,
        146.99651,
        106.99418,
        146.99651,
        517.94529
      ]
    },
    {
      "type": "shape",
      "borderWidth": 1.27823,
      "borderColor": "#7f7f7f",
      "shadowColor": "#1ABC9C",
      "rotation": -3.14159,
      "points": [
        332.33993,
        167.71013,
        330.44259,
        158.17155,
        325.03942,
        150.08514,
        316.95301,
        144.68197,
        307.41444,
        142.78463,
        297.87586,
        144.68197,
        289.78945,
        150.08514,
        284.38628,
        158.17155,
        282.48894,
        167.71013,
        284.38628,
        177.2487,
        289.78945,
        185.33511,
        297.87586,
        190.73828,
        307.41444,
        192.63562,
        316.95301,
        190.73828,
        325.03942,
        185.33511,
        330.44259,
        177.2487,
        332.33993,
        167.71013
      ]
    },
    {
      "type": "shape",
      "background": "#3d3d3d",
      "shadowColor": "#1ABC9C",
      "rotation": -3.14159,
      "points": [
        243.50291,
        516.66705,
        306.1362,
        516.66705,
        324.03143,
        416.96508,
        261.39814,
        416.96508,
        243.50291,
        516.66705,
        243.50291,
        516.66705
      ]
    },
    {
      "type": "shape",
      "background": "#cccccc",
      "shadowColor": "#1ABC9C",
      "rotation": -3.14159,
      "points": [
        215.38184,
        279.5553,
        197.48661,
        296.17229,
        197.48661,
        466.17695,
        215.38184,
        484.07218,
        382.83003,
        484.07218,
        400.08615,
        466.17695,
        400.08615,
        296.17229,
        382.83003,
        278.27707,
        215.38184,
        279.5553,
        215.38184,
        279.5553
      ]
    },
    {
      "type": "shape",
      "background": "#c7c7c7",
      "shadowColor": "#1ABC9C",
      "rotation": -3.14159,
      "points": [
        215.38184,
        314.70664,
        197.48661,
        331.32363,
        197.48661,
        399.06985,
        400.08615,
        484.07218,
        400.08615,
        331.32363,
        382.83003,
        313.42841,
        215.38184,
        314.70664,
        215.38184,
        314.70664
      ]
    },
    {
      "type": "shape",
      "background": "#c2c2c2",
      "shadowColor": "#1ABC9C",
      "rotation": -3.14159,
      "points": [
        215.38184,
        347.94063,
        197.48661,
        364.55763,
        198.76484,
        398.43073,
        400.08615,
        484.07218,
        400.08615,
        364.55763,
        382.83003,
        346.6624,
        215.38184,
        347.94063,
        215.38184,
        347.94063
      ]
    },
    {
      "type": "shape",
      "borderWidth": 1.27823,
      "borderColor": "#000000",
      "shadowColor": "#1ABC9C",
      "rotation": -3.14159,
      "points": [
        215.38184,
        279.5553,
        197.48661,
        296.17229,
        197.48661,
        466.17695,
        215.38184,
        484.07218,
        382.83003,
        484.07218,
        400.08615,
        466.17695,
        400.08615,
        296.17229,
        382.83003,
        278.27707,
        215.38184,
        279.5553
      ]
    },
    {
      "type": "shape",
      "background": "#a8a8a8",
      "shadowColor": "#1ABC9C",
      "rotation": -3.14159,
      "points": [
        250.53318,
        484.07218,
        313.80559,
        484.07218,
        330.42258,
        383.09197,
        267.78929,
        383.09197,
        250.53318,
        484.07218,
        250.53318,
        484.07218
      ]
    },
    {
      "type": "shape",
      "background": "#4c4c4c",
      "shadowColor": "#1ABC9C",
      "rotation": -3.14159,
      "points": [
        238.38999,
        320.45867,
        223.05122,
        342.18859,
        215.38184,
        367.11409,
        214.74272,
        394.59604,
        223.05122,
        420.16065,
        238.38999,
        441.89057,
        260.11991,
        457.86845,
        285.68452,
        466.17695,
        311.88824,
        466.17695,
        337.45285,
        458.50757,
        359.18277,
        441.89057,
        374.52154,
        420.16065,
        382.83003,
        394.59604,
        382.83003,
        367.11409,
        374.52154,
        342.18859,
        359.18277,
        320.45867,
        337.45285,
        303.20256,
        311.88824,
        296.17229,
        285.68452,
        296.17229,
        260.11991,
        304.48079,
        238.38999,
        320.45867,
        238.38999,
        320.45867
      ]
    },
    {
      "type": "shape",
      "borderWidth": 1.27823,
      "borderColor": "#000000",
      "shadowColor": "#1ABC9C",
      "rotation": -3.14159,
      "points": [
        238.38999,
        320.45867,
        223.05122,
        342.18859,
        215.38184,
        367.11409,
        214.74272,
        394.59604,
        223.05122,
        420.16065,
        238.38999,
        441.89057,
        260.11991,
        457.86845,
        285.68452,
        466.17695,
        311.88824,
        466.17695,
        337.45285,
        458.50757,
        359.18277,
        441.89057,
        374.52154,
        420.16065,
        382.83003,
        394.59604,
        382.83003,
        367.11409,
        374.52154,
        342.18859,
        359.18277,
        320.45867,
        337.45285,
        303.20256,
        311.88824,
        296.17229,
        285.68452,
        296.17229,
        260.11991,
        304.48079,
        238.38999,
        320.45867,
        238.38999,
        320.45867
      ]
    },
    {
      "type": "shape",
      "background": "#333333",
      "shadowColor": "#1ABC9C",
      "rotation": -3.14159,
      "points": [
        317.00116,
        464.2596,
        328.50524,
        395.23516,
        324.03143,
        391.40047,
        298.46682,
        384.3702,
        272.2631,
        384.3702,
        267.15017,
        385.64843,
        255.6461,
        466.17695,
        317.00116,
        464.2596,
        317.00116,
        464.2596
      ]
    },
    {
      "type": "shape",
      "background": "#999999",
      "shadowColor": "#1ABC9C",
      "rotation": -3.14159,
      "points": [
        298.46682,
        327.48894,
        327.41066,
        327.48894,
        350.87427,
        351.52484,
        350.87427,
        381.17462,
        350.87427,
        410.8244,
        327.41066,
        434.8603,
        298.46682,
        434.8603,
        269.52299,
        434.8603,
        246.05937,
        410.8244,
        246.05937,
        381.17462,
        246.05937,
        351.52484,
        269.52299,
        327.48894,
        298.46682,
        327.48894,
        298.46682,
        327.48894
      ],
      "segments": [
        1,
        4,
        4,
        4,
        4,
        2
      ]
    },
    {
      "type": "shape",
      "background": "#7f7f7f",
      "shadowColor": "#1ABC9C",
      "rotation": -3.14159,
      "points": [
        261.39814,
        434.8603,
        325.30966,
        434.8603,
        330.42258,
        397.1525,
        317.00116,
        387.56577,
        301.6624,
        381.81374,
        284.40629,
        381.81374,
        269.06752,
        387.56577,
        261.39814,
        434.8603,
        261.39814,
        434.8603
      ]
    },
    {
      "type": "shape",
      "background": "#c7c7cc",
      "shadowColor": "#1ABC9C",
      "rotation": -3.14159,
      "points": [
        330.42258,
        381.17462,
        328.03875,
        369.19026,
        321.25015,
        359.03041,
        311.0903,
        352.24181,
        299.10594,
        349.85797,
        287.12158,
        352.24181,
        276.96172,
        359.03041,
        270.17313,
        369.19026,
        267.78929,
        381.17462,
        270.17313,
        393.15898,
        276.96172,
        403.31884,
        287.12158,
        410.10743,
        299.10594,
        412.49127,
        311.0903,
        410.10743,
        321.25015,
        403.31884,
        328.03875,
        393.15898,
        330.42258,
        381.17462
      ]
    },
    {
      "type": "shape",
      "borderWidth": 1.27823,
      "borderColor": "#000000",
      "shadowColor": "#1ABC9C",
      "rotation": -3.14159,
      "points": [
        330.42258,
        381.17462,
        328.03875,
        369.19026,
        321.25015,
        359.03041,
        311.0903,
        352.24181,
        299.10594,
        349.85797,
        287.12158,
        352.24181,
        276.96172,
        359.03041,
        270.17313,
        369.19026,
        267.78929,
        381.17462,
        270.17313,
        393.15898,
        276.96172,
        403.31884,
        287.12158,
        410.10743,
        299.10594,
        412.49127,
        311.0903,
        410.10743,
        321.25015,
        403.31884,
        328.03875,
        393.15898,
        330.42258,
        381.17462
      ]
    },
    {
      "type": "shape",
      "background": "#000000",
      "shadowColor": "#1ABC9C",
      "rotation": -3.14159,
      "points": [
        287.60186,
        380.53551,
        297.18859,
        391.40047,
        308.05355,
        380.53551,
        297.18859,
        370.94878,
        287.60186,
        380.53551,
        287.60186,
        380.53551
      ]
    },
    {
      "type": "shape",
      "background": "#4c4c4c",
      "shadowColor": "#1ABC9C",
      "rotation": -3.14159,
      "points": [
        108.64959,
        415.68685,
        146.99651,
        388.844,
        146.99651,
        324.93248,
        108.64959,
        351.77532,
        108.64959,
        415.68685,
        108.64959,
        415.68685
      ]
    },
    {
      "type": "shape",
      "background": "#666666",
      "shadowColor": "#1ABC9C",
      "rotation": -3.14159,
      "points": [
        108.64959,
        209.89173,
        146.99651,
        184.32712,
        146.99651,
        350.49709,
        108.64959,
        337.07567,
        108.64959,
        209.89173,
        108.64959,
        209.89173
      ]
    },
    {
      "type": "shape",
      "background": "#7f7f7f",
      "shadowColor": "#1ABC9C",
      "rotation": -3.14159,
      "points": [
        108.64959,
        170.9057,
        146.99651,
        197.74854,
        146.99651,
        120.4156,
        108.64959,
        106.99418,
        108.64959,
        170.9057,
        108.64959,
        170.9057
      ]
    },
    {
      "type": "shape",
      "borderWidth": 1.27823,
      "borderColor": "#000000",
      "shadowColor": "#1ABC9C",
      "rotation": -3.14159,
      "points": [
        94.58906,
        414.40861,
        146.99651,
        414.40861,
        146.99651,
        106.99418,
        94.58906,
        106.99418,
        56.24214,
        131.28056,
        56.24214,
        387.56577,
        94.58906,
        414.40861
      ]
    },
    {
      "type": "shape",
      "borderWidth": 1.27823,
      "borderColor": "#000000",
      "shadowColor": "#1ABC9C",
      "rotation": -3.14159,
      "points": [
        108.64959,
        415.68685,
        108.64959,
        108.27241
      ]
    },
    {
      "type": "shape",
      "background": "#7f7f7f",
      "shadowColor": "#1ABC9C",
      "rotation": -3.14159,
      "points": [
        19.17346,
        18.15716,
        56.24214,
        18.15716,
        56.24214,
        516.66705,
        19.17346,
        516.66705,
        19.17346,
        18.15716,
        19.17346,
        18.15716
      ]
    },
    {
      "type": "shape",
      "background": "#8a8a8a",
      "shadowColor": "#1ABC9C",
      "rotation": -3.14159,
      "points": [
        17.89523,
        44.36088,
        56.24214,
        44.36088,
        56.24214,
        490.46333,
        17.89523,
        490.46333,
        17.89523,
        44.36088,
        17.89523,
        44.36088
      ]
    },
    {
      "type": "shape",
      "background": "#919191",
      "shadowColor": "#1ABC9C",
      "rotation": -3.14159,
      "points": [
        17.89523,
        72.48196,
        56.24214,
        72.48196,
        56.24214,
        462.34226,
        17.89523,
        462.34226,
        17.89523,
        72.48196,
        17.89523,
        72.48196
      ]
    },
    {
      "type": "shape",
      "background": "#9c9c9c",
      "shadowColor": "#1ABC9C",
      "rotation": -3.14159,
      "points": [
        17.89523,
        98.68568,
        56.24214,
        98.68568,
        56.24214,
        436.13853,
        17.89523,
        436.13853,
        17.89523,
        98.68568,
        17.89523,
        98.68568
      ]
    },
    {
      "type": "shape",
      "background": "#a6a6a6",
      "shadowColor": "#1ABC9C",
      "rotation": -3.14159,
      "points": [
        17.89523,
        126.16764,
        56.24214,
        126.16764,
        56.24214,
        408.65658,
        17.89523,
        408.65658,
        17.89523,
        126.16764,
        17.89523,
        126.16764
      ]
    },
    {
      "type": "shape",
      "background": "#b0b0b0",
      "shadowColor": "#1ABC9C",
      "rotation": -3.14159,
      "points": [
        17.89523,
        153.01048,
        56.24214,
        153.01048,
        56.24214,
        381.81374,
        17.89523,
        381.81374,
        17.89523,
        153.01048,
        17.89523,
        153.01048
      ]
    },
    {
      "type": "shape",
      "background": "#b8b8b8",
      "shadowColor": "#1ABC9C",
      "rotation": -3.14159,
      "points": [
        17.89523,
        180.49243,
        56.24214,
        180.49243,
        56.24214,
        354.33178,
        17.89523,
        354.33178,
        17.89523,
        180.49243,
        17.89523,
        180.49243
      ]
    },
    {
      "type": "shape",
      "background": "#c2c2c2",
      "shadowColor": "#1ABC9C",
      "rotation": -3.14159,
      "points": [
        17.89523,
        208.6135,
        56.24214,
        208.6135,
        56.24214,
        326.21071,
        17.89523,
        326.21071,
        17.89523,
        208.6135,
        17.89523,
        208.6135
      ]
    },
    {
      "type": "shape",
      "background": "#cccccc",
      "shadowColor": "#1ABC9C",
      "rotation": -3.14159,
      "points": [
        19.17346,
        234.81723,
        56.24214,
        234.81723,
        56.24214,
        300.00698,
        19.17346,
        300.00698,
        19.17346,
        234.81723,
        19.17346,
        234.81723
      ]
    },
    {
      "type": "shape",
      "background": "#cccccc",
      "shadowColor": "#1ABC9C",
      "rotation": -3.14159,
      "points": [
        19.17346,
        120.4156,
        56.24214,
        120.4156,
        56.24214,
        184.32712,
        19.17346,
        184.32712,
        19.17346,
        120.4156,
        19.17346,
        120.4156
      ]
    },
    {
      "type": "shape",
      "background": "#999999",
      "shadowColor": "#1ABC9C",
      "rotation": -3.14159,
      "points": [
        19.17346,
        145.98021,
        56.24214,
        145.98021,
        56.24214,
        184.32712,
        19.17346,
        184.32712,
        19.17346,
        145.98021,
        19.17346,
        145.98021
      ]
    },
    {
      "type": "shape",
      "borderWidth": 1.27823,
      "borderColor": "#7f7f7f",
      "shadowColor": "#1ABC9C",
      "rotation": -3.14159,
      "points": [
        19.17346,
        120.4156,
        56.24214,
        120.4156,
        56.24214,
        184.32712,
        19.17346,
        184.32712,
        19.17346,
        120.4156
      ]
    },
    {
      "type": "shape",
      "background": "#cccccc",
      "shadowColor": "#1ABC9C",
      "rotation": -3.14159,
      "points": [
        19.17346,
        337.07567,
        56.24214,
        337.07567,
        56.24214,
        402.26542,
        19.17346,
        402.26542,
        19.17346,
        337.07567,
        19.17346,
        337.07567
      ]
    },
    {
      "type": "shape",
      "background": "#999999",
      "shadowColor": "#1ABC9C",
      "rotation": -3.14159,
      "points": [
        19.17346,
        363.91851,
        56.24214,
        363.91851,
        56.24214,
        402.26542,
        19.17346,
        402.26542,
        19.17346,
        363.91851,
        19.17346,
        363.91851
      ]
    },
    {
      "type": "shape",
      "borderWidth": 1.27823,
      "borderColor": "#7f7f7f",
      "shadowColor": "#1ABC9C",
      "rotation": -3.14159,
      "points": [
        19.17346,
        337.07567,
        56.24214,
        337.07567,
        56.24214,
        402.26542,
        19.17346,
        402.26542,
        19.17346,
        337.07567
      ]
    },
    {
      "type": "shape",
      "borderWidth": 1.27823,
      "borderColor": "#000000",
      "shadowColor": "#1ABC9C",
      "rotation": -3.14159,
      "points": [
        19.17346,
        18.15716,
        56.24214,
        18.15716,
        56.24214,
        516.66705,
        19.17346,
        516.66705,
        19.17346,
        18.15716
      ]
    }
  ]
}